[
  {
    "id": 1,
    "name": "Danube",
    "acceptedAnswers": ["danube", "danube river", "donau"],
    "lat": 45.3500,
    "lng": 28.9700,
    "hint": "Europe's second-longest river, flowing through 10 countries from Germany to the Black Sea",
    "difficulty": "easy"
  },
  {
    "id": 2,
    "name": "Rhine",
    "acceptedAnswers": ["rhine", "rhine river", "rhein"],
    "lat": 50.9400,
    "lng": 6.9600,
    "hint": "A major European river flowing from the Swiss Alps through Germany and the Netherlands to the North Sea",
    "difficulty": "easy"
  },
  {
    "id": 3,
    "name": "Volga",
    "acceptedAnswers": ["volga", "volga river"],
    "lat": 48.7000,
    "lng": 44.5000,
    "hint": "The longest river in Europe, flowing through central Russia to the Caspian Sea",
    "difficulty": "medium"
  },
  {
    "id": 4,
    "name": "Thames",
    "acceptedAnswers": ["thames", "thames river", "river thames"],
    "lat": 51.5074,
    "lng": -0.0760,
    "hint": "A famous river flowing through London, England, to the North Sea",
    "difficulty": "easy"
  },
  {
    "id": 5,
    "name": "Seine",
    "acceptedAnswers": ["seine", "seine river"],
    "lat": 48.8600,
    "lng": 2.3500,
    "hint": "A major river flowing through Paris, France, famous for its scenic banks",
    "difficulty": "medium"
  },
  {
    "id": 6,
    "name": "Elbe",
    "acceptedAnswers": ["elbe", "elbe river"],
    "lat": 53.5300,
    "lng": 9.9900,
    "hint": "A major Central European river flowing from the Czech Republic through Germany to the North Sea",
    "difficulty": "hard"
  },
  {
    "id": 7,
    "name": "Po",
    "acceptedAnswers": ["po", "po river"],
    "lat": 44.9500,
    "lng": 11.4000,
    "hint": "Italy's longest river, flowing eastward across the northern plains to the Adriatic Sea",
    "difficulty": "hard"
  },
  {
    "id": 8,
    "name": "Tagus",
    "acceptedAnswers": ["tagus", "tagus river", "tejo", "tajo"],
    "lat": 38.6900,
    "lng": -9.2100,
    "hint": "The longest river on the Iberian Peninsula, flowing through Spain and Portugal to Lisbon",
    "difficulty": "hard"
  },
  {
    "id": 9,
    "name": "Loire",
    "acceptedAnswers": ["loire", "loire river"],
    "lat": 47.2700,
    "lng": -1.5500,
    "hint": "The longest river in France, famous for the chateaux along its valley",
    "difficulty": "medium"
  },
  {
    "id": 10,
    "name": "Dnieper",
    "acceptedAnswers": ["dnieper", "dnieper river", "dnipro"],
    "lat": 50.4500,
    "lng": 30.5200,
    "hint": "A major river flowing through Russia, Belarus, and Ukraine, passing through Kyiv",
    "difficulty": "hard"
  }
]
